libmir/libmir.dll
libmir/capi.py
libmir/__init__.py
libmir-0.1.0a3.dist-info/top_level.txt
libmir-0.1.0a3.dist-info/LICENSE
libmir-0.1.0a3.dist-info/RECORD
libmir-0.1.0a3.dist-info/WHEEL
libmir-0.1.0a3.dist-info/METADATA
