Metadata-Version: 2.1
Name: libmir
Version: 0.1.0a3
Summary: Python bindings for MIR JIT.
Home-page: https://github.com/eliphatfs/libmir
Author: flandre.info
Author-email: flandre@scarletx.cn
License: UNKNOWN
Platform: UNKNOWN
Classifier: Programming Language :: Python :: 3 :: Only
Classifier: License :: OSI Approved :: Apache Software License
Requires-Python: ~=3.6
License-File: LICENSE
